.editorconfig
.travis.yml
AUTHORS
CONTRIBUTING.rst
ChangeLog
LICENSE
README.rst
requirements.txt
setup.cfg
setup.py
test-requirements.txt
tox.ini
sphinxcontrib/__init__.py
sphinxcontrib/prettyspecialmethods.py
sphinxcontrib_prettyspecialmethods.egg-info/PKG-INFO
sphinxcontrib_prettyspecialmethods.egg-info/SOURCES.txt
sphinxcontrib_prettyspecialmethods.egg-info/dependency_links.txt
sphinxcontrib_prettyspecialmethods.egg-info/namespace_packages.txt
sphinxcontrib_prettyspecialmethods.egg-info/not-zip-safe
sphinxcontrib_prettyspecialmethods.egg-info/pbr.json
sphinxcontrib_prettyspecialmethods.egg-info/requires.txt
sphinxcontrib_prettyspecialmethods.egg-info/top_level.txt
tests/conftest.py
tests/test_implemented.py
tests/test_plaintext.py
tests/test-simple/conf.py
tests/test-simple/index.rst