Metadata-Version: 1.2
Name: sphinxcontrib-prettyspecialmethods
Version: 0.1.0
Summary: Shows special methods as the python syntax that invokes them
Home-page: https://github.com/sphinx-contrib/prettyspecialmethods
Author: Thomas Smith
Maintainer: Eric Wieser
License: UNKNOWN
Project-URL: Bug Tracker, https://github.com/sphinx-contrib/prettyspecialmethods/issues
Project-URL: Source Code, https://github.com/sphinx-contrib/prettyspecialmethods
Platform: UNKNOWN
Classifier: Development Status :: 3 - Alpha
Classifier: Environment :: Console
Classifier: Environment :: Web Environment
Classifier: Framework :: Sphinx :: Extension
Classifier: Intended Audience :: Developers
Classifier: License :: OSI Approved :: MIT License
Classifier: Operating System :: OS Independent
Classifier: Programming Language :: Python
Classifier: Programming Language :: Python :: 3
Classifier: Programming Language :: Python :: 3.6
Classifier: Programming Language :: Python :: 3.7
Classifier: Programming Language :: Python :: 3.8
Classifier: Programming Language :: Python :: 3.9
Classifier: Topic :: Documentation
Classifier: Topic :: Documentation :: Sphinx
Classifier: Topic :: Utilities
